Metadata-Version: 2.1
Name: flake8-assignment-expressions
Version: 1.0.0
Summary: A flake8 plugin that disallows assignment expressions
Home-page: https://github.com/GambitingMan/flake8_assignment_expressions
Author: Nermin Dedovic
Author-email: nermin_dedovic@hotmail.com
License: MIT
Platform: UNKNOWN
Classifier: License :: OSI Approved :: MIT License
Classifier: Programming Language :: Python :: 3
Classifier: Programming Language :: Python :: 3 :: Only
Classifier: Programming Language :: Python :: 3.8
Classifier: Programming Language :: Python :: 3.9
Classifier: Programming Language :: Python :: 3.10
Requires-Python: >=3.8
License-File: LICENSE
Requires-Dist: flake8 (>=3.7)
